swisseph.cp38-win_amd64.pyd
pyswisseph-2.10.3.2.dist-info/LICENSE.txt
pyswisseph-2.10.3.2.dist-info/METADATA
pyswisseph-2.10.3.2.dist-info/WHEEL
pyswisseph-2.10.3.2.dist-info/top_level.txt
pyswisseph-2.10.3.2.dist-info/RECORD
