Metadata-Version: 2.1
Name: pyswisseph
Version: 2.10.3.2
Summary: Python extension to the Swiss Ephemeris
Home-page: https://astrorigin.com/pyswisseph
Author: Stanislas Marquis
Author-email: stan@astrorigin.com
License: UNKNOWN
Download-URL: https://pypi.org/project/pyswisseph
Keywords: Astrology Ephemeris Swisseph
Platform: UNKNOWN
Classifier: Development Status :: 3 - Alpha
Classifier: Intended Audience :: Developers
Classifier: Intended Audience :: Religion
Classifier: License :: OSI Approved :: GNU Affero General Public License v3
Classifier: Programming Language :: C
Classifier: Programming Language :: Python
Classifier: Programming Language :: Python :: 2
Classifier: Programming Language :: Python :: 3
Classifier: Topic :: Religion
Classifier: Topic :: Scientific/Engineering :: Astronomy
Classifier: Topic :: Software Development :: Libraries :: Python Modules
Requires-Python: >=3.5
License-File: LICENSE.txt
